{
  "$schema": "https://developer.microsoft.com/json-schemas/fabric/item/report/definition/visualContainer/2.4.0/schema.json",
  "name": "40cdc3d20a0c55645563",
  "position": {
    "x": 253.6762481089259,
    "y": 529.62178517397888,
    "z": 35000,
    "height": 60.998487140695921,
    "width": 137.48865355521937,
    "tabOrder": 30000
  },
  "visual": {
    "visualType": "cardVisual",
    "query": {
      "queryState": {
        "Data": {
          "projections": [
            {
              "field": {
                "Measure": {
                  "Expression": {
                    "SourceRef": {
                      "Entity": "Medidas"
                    }
                  },
                  "Property": "Top 2 - Imagem"
                }
              },
              "queryRef": "Medidas.Top 2 - Imagem",
              "nativeQueryRef": "Top 2 - Imagem"
            }
          ]
        }
      }
    },
    "objects": {
      "image": [
        {
          "properties": {
            "show": {
              "expr": {
                "Literal": {
                  "Value": "true"
                }
              }
            },
            "imageType": {
              "expr": {
                "Literal": {
                  "Value": "'imageUrl'"
                }
              }
            },
            "imageUrl": {
              "expr": {
                "Measure": {
                  "Expression": {
                    "SourceRef": {
                      "Entity": "Medidas"
                    }
                  },
                  "Property": "Top 2 - Imagem"
                }
              }
            },
            "verticalAlignment": {
              "expr": {
                "Literal": {
                  "Value": "'middle'"
                }
              }
            },
            "fit": {
              "expr": {
                "Literal": {
                  "Value": "'Normal'"
                }
              }
            },
            "size": {
              "expr": {
                "Literal": {
                  "Value": "32L"
                }
              }
            }
          },
          "selector": {
            "id": "default"
          }
        }
      ],
      "value": [
        {
          "properties": {
            "show": {
              "expr": {
                "Literal": {
                  "Value": "true"
                }
              }
            }
          }
        },
        {
          "properties": {
            "fontSize": {
              "expr": {
                "Literal": {
                  "Value": "8D"
                }
              }
            },
            "fontColor": {
              "solid": {
                "color": {
                  "expr": {
                    "ThemeDataColor": {
                      "ColorId": 0,
                      "Percent": 0
                    }
                  }
                }
              }
            },
            "horizontalAlignment": {
              "expr": {
                "Literal": {
                  "Value": "'center'"
                }
              }
            }
          },
          "selector": {
            "id": "default"
          }
        }
      ],
      "outline": [
        {
          "properties": {
            "show": {
              "expr": {
                "Literal": {
                  "Value": "false"
                }
              }
            }
          },
          "selector": {
            "id": "default"
          }
        }
      ],
      "fillCustom": [
        {
          "properties": {
            "show": {
              "expr": {
                "Literal": {
                  "Value": "false"
                }
              }
            }
          }
        }
      ],
      "label": [
        {
          "properties": {
            "show": {
              "expr": {
                "Literal": {
                  "Value": "false"
                }
              }
            }
          },
          "selector": {
            "id": "default"
          }
        }
      ]
    },
    "visualContainerObjects": {
      "background": [
        {
          "properties": {
            "show": {
              "expr": {
                "Literal": {
                  "Value": "false"
                }
              }
            }
          }
        }
      ]
    },
    "drillFilterOtherVisuals": true
  },
  "filterConfig": {
    "filters": [
      {
        "name": "f1c43e3068829c1669bb",
        "field": {
          "Measure": {
            "Expression": {
              "SourceRef": {
                "Entity": "Medidas"
              }
            },
            "Property": "Top 2 - Imagem"
          }
        },
        "type": "Advanced"
      }
    ]
  }
}